DataHive/__init__.py
DataHive/__main__.py
DataHive/lib/commands/abstract_command.py
DataHive/lib/commands/clear_command.py
DataHive/lib/commands/command_factory.py
DataHive/lib/commands/create_command.py
DataHive/lib/commands/delete_command.py
DataHive/lib/commands/get_command.py
DataHive/lib/commands/set_command.py
DataHive/lib/commands/__pycache__/abstract_command.cpython-310.pyc
DataHive/lib/commands/__pycache__/clear_command.cpython-310.pyc
DataHive/lib/commands/__pycache__/command_factory.cpython-310.pyc
DataHive/lib/commands/__pycache__/create_command.cpython-310.pyc
DataHive/lib/commands/__pycache__/delete_command.cpython-310.pyc
DataHive/lib/commands/__pycache__/get_command.cpython-310.pyc
DataHive/lib/commands/__pycache__/set_command.cpython-310.pyc
DataHive/lib/input_adaptors/iadaptor.py
DataHive/lib/input_adaptors/input.py
DataHive/lib/input_adaptors/parser_adaptor.py
DataHive/lib/input_adaptors/__pycache__/iadaptor.cpython-310.pyc
DataHive/lib/input_adaptors/__pycache__/input.cpython-310.pyc
DataHive/lib/input_adaptors/__pycache__/parser_adaptor.cpython-310.pyc
DataHive/lib/model/database.py
DataHive/lib/model/index.py
DataHive/lib/model/index_value.py
DataHive/lib/model/primary_key_index.py
DataHive/lib/model/row.py
DataHive/lib/model/schema_keys.py
DataHive/lib/model/table.py
DataHive/lib/model/table_metadata.py
DataHive/lib/model/__pycache__/database.cpython-310.pyc
DataHive/lib/model/__pycache__/index.cpython-310.pyc
DataHive/lib/model/__pycache__/index_value.cpython-310.pyc
DataHive/lib/model/__pycache__/primary_key_index.cpython-310.pyc
DataHive/lib/model/__pycache__/row.cpython-310.pyc
DataHive/lib/model/__pycache__/schema_keys.cpython-310.pyc
DataHive/lib/model/__pycache__/table.cpython-310.pyc
DataHive/lib/model/__pycache__/table_metadata.cpython-310.pyc
DataHive/lib/output/exceptions.py
DataHive/lib/output/output_message.py
DataHive/lib/output/status.py
DataHive/lib/output/__pycache__/exceptions.cpython-310.pyc
DataHive-1.0.0.dist-info/LICENSE
DataHive-1.0.0.dist-info/METADATA
DataHive-1.0.0.dist-info/WHEEL
DataHive-1.0.0.dist-info/entry_points.txt
DataHive-1.0.0.dist-info/top_level.txt
DataHive-1.0.0.dist-info/RECORD
